{
  "url": "https://www.databricks.com/company/careers/open-positions?department=University%20Recruiting&location=Washington",
  "contentHash": "c04c4312b093ac57ee5c159e4a3faba4",
  "content": ".sidenav::-webkit-scrollbar {\n\n      width: 8px;\n    }\n    .sidenav::-webkit-scrollbar-thumb {\n      background: #90a5b1;\n      background-clip: padding-box;\n      border-radius: 14px;\n    }\n  OverviewCultureBenefitsInclusionEngineeringResearchGo to MarketInternships & Early CareersOpen PositionsRecruitment FraudCurrent job openings at Databricks\nUniversity RecruitingWashingtonNo Jobs found.Please change your search criteria and try again.",
  "timestamp": "2025-03-26T06:11:06.372Z",
  "previousTimestamp": "2025-03-23T00:58:08.989Z"
}